LICENSE
MANIFEST.in
README.md
setup.py
pyprelude/__init__.py
pyprelude/file_system.py
pyprelude/platform.py
pyprelude/process.py
pyprelude/temp_util.py
pyprelude/url.py
pyprelude/util.py
pyprelude.egg-info/PKG-INFO
pyprelude.egg-info/SOURCES.txt
pyprelude.egg-info/dependency_links.txt
pyprelude.egg-info/not-zip-safe
pyprelude.egg-info/top_level.txt