Metadata-Version: 1.1
Name: pyprelude
Version: 0.9
Summary: General-purpose Python support functions
Home-page: https://github.com/rcook/pyprelude
Author: Richard Cook
Author-email: rcook@rcook.org
License: MIT
Platform: UNKNOWN
Classifier: Development Status :: 3 - Alpha
Classifier: License :: OSI Approved :: MIT License
Classifier: Programming Language :: Python :: 2.7
